shadowwalker/__init__.py
shadowwalker/core.py
shadowwalker/utils.py
shadowwalker/__metadata__/DISCLIAIMER.md
shadowwalker/__metadata__/LICENSE
shadowwalker/__metadata__/README.md
shadowwalker/__metadata__/__init__.py
shadowwalker/__metadata__/requirements.txt
shadowwalker/pkg_data/Country.mmdb
shadowwalker/pkg_data/bench.json
shadowwalker/pkg_data/bench_mega.json
shadowwalker/pkg_data/bench_pixeldrain.json
shadowwalker/pkg_data/cache.db
shadowwalker/pkg_data/clash.bin
shadowwalker/pkg_data/clash.exe
shadowwalker/pkg_data/gse.json
shadowwalker-1.1.0.dist-info/METADATA
shadowwalker-1.1.0.dist-info/WHEEL
shadowwalker-1.1.0.dist-info/top_level.txt
shadowwalker-1.1.0.dist-info/RECORD
