Metadata-Version: 2.1
Name: shadowwalker
Version: 1.1.0
Summary: Shadow Walker, a python API to run [slash](https://github.com/Dreamacro/clash) with quick presets. Best to bypass rate limit and IP block.
Home-page: http://code.foxe6.kozow.com/shadowwalker/
Author: f̣ộx̣ệ6
Author-email: foxe6@pm.me
License: AGPL-3.0
Project-URL: Sourcecode, http://code.foxe6.kozow.com/shadowwalker.zip
Project-URL: Documentation, http://code.foxe6.kozow.com/shadowwalker/docs/
Project-URL: Example, http://code.foxe6.kozow.com/shadowwalker/test/
Project-URL: Funding, https://paypal.me/foxe6
Project-URL: Say Thanks!, https://saythanks.io/to/foxe6
Keywords: clash proxy shadowsocks shadowsocksr v2ray vless vmess trojan vpn socks http https mega nz meganz
Platform: UNKNOWN
Classifier: Programming Language :: Python :: 3.9
Classifier: Topic :: Utilities
Classifier: Natural Language :: English
Classifier: Intended Audience :: Developers
Classifier: License :: OSI Approved :: GNU Affero General Public License v3
Classifier: Operating System :: MacOS
Classifier: Operating System :: POSIX
Classifier: Operating System :: Microsoft :: Windows :: Windows 10
Classifier: Development Status :: 5 - Production/Stable
Requires-Python: >=3.5
Requires-Dist: requests (>=0.0.1)
Requires-Dist: omnitools (>=0.0.1)
Requires-Dist: threadwrapper (>=0.0.1)
